omsatyawanpathak/__init__.py
omsatyawanpathak/omsatyawanpathak.py
omsatyawanpathak-0.1.0.dist-info/LICENSE
omsatyawanpathak-0.1.0.dist-info/METADATA
omsatyawanpathak-0.1.0.dist-info/WHEEL
omsatyawanpathak-0.1.0.dist-info/top_level.txt
omsatyawanpathak-0.1.0.dist-info/RECORD
